{
  "last_updated": "2026-03-24 08:07 UTC",
  "labels": [
    "00:00",
    "00:30",
    "01:00",
    "01:30",
    "02:00",
    "02:30",
    "03:00",
    "03:30",
    "04:00",
    "04:30",
    "05:00",
    "05:30",
    "06:00",
    "06:30",
    "07:00",
    "07:30",
    "08:00",
    "08:30",
    "09:00",
    "09:30",
    "10:00",
    "10:30",
    "11:00",
    "11:30",
    "12:00",
    "12:30",
    "13:00",
    "13:30",
    "14:00",
    "14:30",
    "15:00",
    "15:30",
    "16:00",
    "16:30",
    "17:00",
    "17:30",
    "18:00",
    "18:30",
    "19:00",
    "19:30",
    "20:00",
    "20:30",
    "21:00",
    "21:30",
    "22:00",
    "22:30",
    "23:00",
    "23:30"
  ],
  "values": [
    72,
    71,
    69,
    68,
    68,
    66,
    61,
    55,
    53,
    52,
    55,
    61,
    75,
    60,
    64,
    54,
    54,
    52,
    51,
    49,
    47,
    46,
    47,
    47,
    49,
    47,
    48,
    48,
    51,
    53,
    54,
    58,
    64,
    68,
    75,
    79,
    86,
    88,
    80,
    66,
    59,
    59,
    58,
    55,
    53,
    50,
    51,
    53
  ],
  "actual_values": [
    72.0,
    71.0,
    69.0,
    68.0,
    68.0,
    66.0,
    61.0,
    55.0,
    53.0,
    52.0,
    55.0,
    61.0,
    75.0,
    60.0,
    64.0,
    null,
    null,
    null,
    null,
    null,
    null,
    null,
    null,
    null,
    null,
    null,
    null,
    null,
    null,
    null,
    null,
    null,
    null,
    null,
    null,
    null,
    null,
    null,
    null,
    null,
    null,
    null,
    null,
    null,
    null,
    null,
    null,
    null
  ],
  "forecast_values": [
    67,
    65,
    65,
    65,
    63,
    62,
    66,
    67,
    61,
    52,
    51,
    47,
    47,
    53,
    66,
    54,
    54,
    52,
    51,
    49,
    47,
    46,
    47,
    47,
    49,
    47,
    48,
    48,
    51,
    53,
    54,
    58,
    64,
    68,
    75,
    79,
    86,
    88,
    80,
    66,
    59,
    59,
    58,
    55,
    53,
    50,
    51,
    53
  ]
}